silly_code/__init__.py
silly_code-0.1.0.dist-info/METADATA
silly_code-0.1.0.dist-info/WHEEL
silly_code-0.1.0.dist-info/RECORD
