Metadata-Version: 2.4
Name: silly_code
Version: 0.1.0
Author-email: Jared Galloway <jaredgalloway07@gmail.com>
Requires-Python: >=3.11
Requires-Dist: numpy
